edi_core/__init__.py
edi_core/cloud/README.md
edi_core/cloud/__init__.py
edi_core/cloud/oss.py
edi_core/db/__init__.py
edi_core/db/simple_kv.py
edi_core/db/tinydb.py
edi_core/scm/__init__.py
edi_core/scm/git.py
edi_core/utils/__init__.py
edi_core/utils/assertions.py
edi_core/utils/audio.py
edi_core/utils/cli.py
edi_core/utils/datetime.py
edi_core/utils/encoding.py
edi_core/utils/env.py
edi_core/utils/file.py
edi_core/utils/filetype.py
edi_core/utils/hash.py
edi_core/win/__init__.py
edi_core/win/control.py
edi_core/win/reg.py
edi_core-1.1.0.dist-info/METADATA
edi_core-1.1.0.dist-info/WHEEL
edi_core-1.1.0.dist-info/RECORD
