Metadata-Version: 2.4
Name: edi-core
Version: 1.1.0
Summary: 
License: MIT
Author: LtttAZ
Author-email: louis_zhang_1303@126.com
Requires-Python: ==3.13.2
Classifier: License :: OSI Approved :: MIT License
Classifier: Programming Language :: Python :: 3
Requires-Dist: alibabacloud-oss-v2 (>=1.2.1,<2.0.0)
Requires-Dist: filetype (>=1.2.0,<2.0.0)
Requires-Dist: gitpython (>=3.1.45,<4.0.0)
Requires-Dist: loguru (>=0.7.3,<0.8.0)
Requires-Dist: matplotlib (>=3.10.7,<4.0.0)
Requires-Dist: packaging (>=25.0,<26.0)
Requires-Dist: pendulum (>=3.1.0,<4.0.0)
Requires-Dist: poetry-core (>=2.2.1,<3.0.0)
Requires-Dist: pyautogui (>=0.9.54,<0.10.0)
Requires-Dist: pydantic (>=2.12.4,<3.0.0)
Requires-Dist: python-dotenv (>=1.2.1,<2.0.0)
Requires-Dist: requests (>=2.32.5,<3.0.0)
Requires-Dist: tinydb (>=4.8.2,<5.0.0)
